quadrosdesaude/__init__.py
quadrosdesaude/core.py
quadrosdesaude/datasus.cp313-win_amd64.pyd
quadrosdesaude/utils.py
quadrosdesaude/c_src/blast.c
quadrosdesaude/c_src/decompress.c
quadrosdesaude/conversao/__init__.py
quadrosdesaude/conversao/conversor.py
quadrosdesaude/conversao/orquestrador.py
quadrosdesaude/conversao/parser.py
quadrosdesaude/extracao/__init__.py
quadrosdesaude/extracao/ftp.py
quadrosdesaude-0.1.6.dist-info/licenses/LICENSE.md
quadrosdesaude-0.1.6.dist-info/METADATA
quadrosdesaude-0.1.6.dist-info/WHEEL
quadrosdesaude-0.1.6.dist-info/top_level.txt
quadrosdesaude-0.1.6.dist-info/RECORD
