Metadata-Version: 2.4
Name: quadrosdesaude
Version: 0.1.6
Summary: Ferramentas para processar dados do Datasus (Sistema Público de Saúde).
Author-email: André Quadros <andre@quadrosdesaude.com.br>
License-Expression: MIT
Project-URL: Homepage, https://quadrosdesaude.com.br
Requires-Python: >=3.10
License-File: LICENSE.md
Dynamic: license-file
